<?xml version="1.0" encoding="UTF-8"?>
<users>
  <user id="2345" contextid="3648">
    <username>5ddc13ca-f36f-4470-8d0a-0076773dd2af</username>
    <idnumber></idnumber>
    <email>amy.poland@maine.gov</email>
    <icq></icq>
    <skype></skype>
    <yahoo></yahoo>
    <aim></aim>
    <msn></msn>
    <phone1></phone1>
    <phone2></phone2>
    <institution></institution>
    <department></department>
    <address></address>
    <city></city>
    <country></country>
    <lastip>67.242.189.164</lastip>
    <picture>156835</picture>
    <url></url>
    <description></description>
    <descriptionformat>0</descriptionformat>
    <imagealt></imagealt>
    <auth>saml2</auth>
    <firstnamephonetic></firstnamephonetic>
    <lastnamephonetic></lastnamephonetic>
    <middlename></middlename>
    <alternatename></alternatename>
    <firstname>Amy</firstname>
    <lastname>Poland</lastname>
    <confirmed>1</confirmed>
    <policyagreed>0</policyagreed>
    <deleted>0</deleted>
    <lang>en_us</lang>
    <theme></theme>
    <timezone>99</timezone>
    <firstaccess>1394659238</firstaccess>
    <lastaccess>1707770594</lastaccess>
    <lastlogin>1704741737</lastlogin>
    <currentlogin>1707763225</currentlogin>
    <mailformat>1</mailformat>
    <maildigest>1</maildigest>
    <maildisplay>2</maildisplay>
    <autosubscribe>1</autosubscribe>
    <trackforums>1</trackforums>
    <timecreated>1394659238</timecreated>
    <timemodified>1707763225</timemodified>
    <trustbitmask>0</trustbitmask>
    <custom_fields>
      <custom_field id="1">
        <field_name>starusername</field_name>
        <field_type>text</field_type>
        <field_data>alpoland</field_data>
      </custom_field>
    </custom_fields>
    <tags>
    </tags>
    <preferences>
      <preference id="20409">
        <name>core_message_migrate_data</name>
        <value>1</value>
      </preference>
      <preference id="17037">
        <name>filepicker_recentlicense</name>
        <value>allrightsreserved</value>
      </preference>
      <preference id="17036">
        <name>filepicker_recentrepository</name>
        <value>3</value>
      </preference>
      <preference id="17038">
        <name>htmleditor</name>
        <value></value>
      </preference>
      <preference id="13666">
        <name>topcoll_toggle_126</name>
        <value>_Z</value>
      </preference>
      <preference id="22893">
        <name>topcoll_toggle_131</name>
        <value>YZ</value>
      </preference>
      <preference id="22308">
        <name>topcoll_toggle_132</name>
        <value>::</value>
      </preference>
      <preference id="33592">
        <name>topcoll_toggle_238</name>
        <value>Z</value>
      </preference>
      <preference id="23514">
        <name>topcoll_toggle_239</name>
        <value></value>
      </preference>
      <preference id="23513">
        <name>topcoll_toggle_240</name>
        <value></value>
      </preference>
      <preference id="55696">
        <name>topcoll_toggle_241</name>
        <value></value>
      </preference>
      <preference id="44826">
        <name>topcoll_toggle_257</name>
        <value>JJ</value>
      </preference>
      <preference id="48181">
        <name>topcoll_toggle_259</name>
        <value>j</value>
      </preference>
      <preference id="55695">
        <name>topcoll_toggle_263</name>
        <value>Z:</value>
      </preference>
      <preference id="52438">
        <name>topcoll_toggle_273</name>
        <value>;:</value>
      </preference>
      <preference id="59810">
        <name>topcoll_toggle_299</name>
        <value>B</value>
      </preference>
    </preferences>
    <roles>
      <role_overrides>
      </role_overrides>
      <role_assignments>
      </role_assignments>
    </roles>
  </user>
  <user id="7114" contextid="13235">
    <username>232856cd-6393-4405-a0b9-ecb0956c8506</username>
    <idnumber></idnumber>
    <email>trevi.hardy@cte.idaho.gov</email>
    <icq></icq>
    <skype></skype>
    <yahoo></yahoo>
    <aim></aim>
    <msn></msn>
    <phone1></phone1>
    <phone2></phone2>
    <institution></institution>
    <department></department>
    <address></address>
    <city></city>
    <country>US</country>
    <lastip>164.165.109.125</lastip>
    <picture>0</picture>
    <url></url>
    <description></description>
    <descriptionformat>1</descriptionformat>
    <imagealt></imagealt>
    <auth>saml2</auth>
    <firstnamephonetic></firstnamephonetic>
    <lastnamephonetic></lastnamephonetic>
    <middlename></middlename>
    <alternatename></alternatename>
    <firstname>Trevi</firstname>
    <lastname>Hardy</lastname>
    <confirmed>1</confirmed>
    <policyagreed>0</policyagreed>
    <deleted>0</deleted>
    <lang>en_us</lang>
    <theme></theme>
    <timezone>99</timezone>
    <firstaccess>1432324598</firstaccess>
    <lastaccess>1707756176</lastaccess>
    <lastlogin>1705614318</lastlogin>
    <currentlogin>1707754375</currentlogin>
    <mailformat>1</mailformat>
    <maildigest>0</maildigest>
    <maildisplay>1</maildisplay>
    <autosubscribe>1</autosubscribe>
    <trackforums>0</trackforums>
    <timecreated>1432324595</timecreated>
    <timemodified>1707754375</timemodified>
    <trustbitmask>0</trustbitmask>
    <custom_fields>
      <custom_field id="1">
        <field_name>starusername</field_name>
        <field_type>text</field_type>
        <field_data>Trevi Hardy</field_data>
      </custom_field>
    </custom_fields>
    <tags>
    </tags>
    <preferences>
      <preference id="21896">
        <name>core_message_migrate_data</name>
        <value>1</value>
      </preference>
      <preference id="14227">
        <name>topcoll_toggle_137</name>
        <value>j</value>
      </preference>
      <preference id="28921">
        <name>topcoll_toggle_138</name>
        <value>v</value>
      </preference>
      <preference id="15278">
        <name>topcoll_toggle_139</name>
        <value>v</value>
      </preference>
      <preference id="59788">
        <name>topcoll_toggle_299</name>
        <value>j</value>
      </preference>
    </preferences>
    <roles>
      <role_overrides>
      </role_overrides>
      <role_assignments>
      </role_assignments>
    </roles>
  </user>
  <user id="12905" contextid="20807">
    <username>2632d924-7cd8-4476-a3d1-b02f38cd7306</username>
    <idnumber></idnumber>
    <email>swhalen@air.org</email>
    <icq></icq>
    <skype></skype>
    <yahoo></yahoo>
    <aim></aim>
    <msn></msn>
    <phone1></phone1>
    <phone2></phone2>
    <institution></institution>
    <department></department>
    <address></address>
    <city></city>
    <country>US</country>
    <lastip>98.183.166.16</lastip>
    <picture>208435</picture>
    <url></url>
    <description></description>
    <descriptionformat>1</descriptionformat>
    <imagealt></imagealt>
    <auth>saml2</auth>
    <firstnamephonetic></firstnamephonetic>
    <lastnamephonetic></lastnamephonetic>
    <middlename></middlename>
    <alternatename></alternatename>
    <firstname>Sudie</firstname>
    <lastname>Whalen</lastname>
    <confirmed>1</confirmed>
    <policyagreed>0</policyagreed>
    <deleted>0</deleted>
    <lang>en_us</lang>
    <theme></theme>
    <timezone>99</timezone>
    <firstaccess>1480359742</firstaccess>
    <lastaccess>1707778279</lastaccess>
    <lastlogin>1707672732</lastlogin>
    <currentlogin>1707758040</currentlogin>
    <mailformat>1</mailformat>
    <maildigest>0</maildigest>
    <maildisplay>2</maildisplay>
    <autosubscribe>1</autosubscribe>
    <trackforums>0</trackforums>
    <timecreated>1480359739</timecreated>
    <timemodified>1707758040</timemodified>
    <trustbitmask>0</trustbitmask>
    <custom_fields>
      <custom_field id="1">
        <field_name>starusername</field_name>
        <field_type>text</field_type>
        <field_data>Sudie Whalen</field_data>
      </custom_field>
    </custom_fields>
    <tags>
    </tags>
    <preferences>
      <preference id="23582">
        <name>core_message_migrate_data</name>
        <value>1</value>
      </preference>
      <preference id="38344">
        <name>coursecat_management_perpage</name>
        <value>999</value>
      </preference>
      <preference id="45156">
        <name>filepicker_recentlicense</name>
        <value>allrightsreserved</value>
      </preference>
      <preference id="45155">
        <name>filepicker_recentrepository</name>
        <value>3</value>
      </preference>
      <preference id="38842">
        <name>htmleditor</name>
        <value>tinymce</value>
      </preference>
      <preference id="38065">
        <name>ifirst</name>
        <value>M</value>
      </preference>
      <preference id="38066">
        <name>ilast</name>
        <value>G</value>
      </preference>
      <preference id="38759">
        <name>lesson_view</name>
        <value>full</value>
      </preference>
      <preference id="36182">
        <name>topcoll_toggle_126</name>
        <value>yy</value>
      </preference>
      <preference id="36398">
        <name>topcoll_toggle_127</name>
        <value>yy</value>
      </preference>
      <preference id="35134">
        <name>topcoll_toggle_131</name>
        <value>yy</value>
      </preference>
      <preference id="36403">
        <name>topcoll_toggle_132</name>
        <value>yy</value>
      </preference>
      <preference id="36402">
        <name>topcoll_toggle_133</name>
        <value>yy</value>
      </preference>
      <preference id="9277">
        <name>topcoll_toggle_137</name>
        <value>v</value>
      </preference>
      <preference id="17199">
        <name>topcoll_toggle_138</name>
        <value>y</value>
      </preference>
      <preference id="36394">
        <name>topcoll_toggle_139</name>
        <value>y</value>
      </preference>
      <preference id="38248">
        <name>topcoll_toggle_155</name>
        <value>yy</value>
      </preference>
      <preference id="36393">
        <name>topcoll_toggle_156</name>
        <value>y</value>
      </preference>
      <preference id="12983">
        <name>topcoll_toggle_157</name>
        <value>y</value>
      </preference>
      <preference id="9374">
        <name>topcoll_toggle_158</name>
        <value>y</value>
      </preference>
      <preference id="9371">
        <name>topcoll_toggle_159</name>
        <value>r</value>
      </preference>
      <preference id="36245">
        <name>topcoll_toggle_168</name>
        <value>b</value>
      </preference>
      <preference id="38337">
        <name>topcoll_toggle_169</name>
        <value>::</value>
      </preference>
      <preference id="38642">
        <name>topcoll_toggle_190</name>
        <value>:Z</value>
      </preference>
      <preference id="54619">
        <name>topcoll_toggle_191</name>
        <value>::</value>
      </preference>
      <preference id="36232">
        <name>topcoll_toggle_203</name>
        <value>y</value>
      </preference>
      <preference id="38619">
        <name>topcoll_toggle_212</name>
        <value>::</value>
      </preference>
      <preference id="38624">
        <name>topcoll_toggle_216</name>
        <value>:Z</value>
      </preference>
      <preference id="38626">
        <name>topcoll_toggle_219</name>
        <value>::</value>
      </preference>
      <preference id="38632">
        <name>topcoll_toggle_220</name>
        <value>::</value>
      </preference>
      <preference id="38631">
        <name>topcoll_toggle_221</name>
        <value>::</value>
      </preference>
      <preference id="38625">
        <name>topcoll_toggle_222</name>
        <value>::</value>
      </preference>
      <preference id="38628">
        <name>topcoll_toggle_223</name>
        <value>::</value>
      </preference>
      <preference id="38620">
        <name>topcoll_toggle_224</name>
        <value>yy</value>
      </preference>
      <preference id="38415">
        <name>topcoll_toggle_225</name>
        <value>::</value>
      </preference>
      <preference id="38621">
        <name>topcoll_toggle_226</name>
        <value>::</value>
      </preference>
      <preference id="38629">
        <name>topcoll_toggle_227</name>
        <value>::</value>
      </preference>
      <preference id="38622">
        <name>topcoll_toggle_228</name>
        <value>::</value>
      </preference>
      <preference id="38623">
        <name>topcoll_toggle_231</name>
        <value>::</value>
      </preference>
      <preference id="38630">
        <name>topcoll_toggle_232</name>
        <value>::</value>
      </preference>
      <preference id="38627">
        <name>topcoll_toggle_235</name>
        <value>::</value>
      </preference>
      <preference id="38633">
        <name>topcoll_toggle_236</name>
        <value>::</value>
      </preference>
      <preference id="36392">
        <name>topcoll_toggle_237</name>
        <value>Z</value>
      </preference>
      <preference id="36391">
        <name>topcoll_toggle_238</name>
        <value>Z</value>
      </preference>
      <preference id="36399">
        <name>topcoll_toggle_239</name>
        <value></value>
      </preference>
      <preference id="36400">
        <name>topcoll_toggle_240</name>
        <value></value>
      </preference>
      <preference id="36401">
        <name>topcoll_toggle_241</name>
        <value></value>
      </preference>
      <preference id="38408">
        <name>topcoll_toggle_242</name>
        <value>Z:</value>
      </preference>
      <preference id="38634">
        <name>topcoll_toggle_243</name>
        <value>::</value>
      </preference>
      <preference id="35488">
        <name>topcoll_toggle_244</name>
        <value></value>
      </preference>
      <preference id="41455">
        <name>topcoll_toggle_245</name>
        <value></value>
      </preference>
      <preference id="38416">
        <name>topcoll_toggle_248</name>
        <value>::</value>
      </preference>
      <preference id="38543">
        <name>topcoll_toggle_249</name>
        <value>::</value>
      </preference>
      <preference id="38540">
        <name>topcoll_toggle_250</name>
        <value>::</value>
      </preference>
      <preference id="37735">
        <name>topcoll_toggle_251</name>
        <value></value>
      </preference>
      <preference id="37414">
        <name>topcoll_toggle_252</name>
        <value></value>
      </preference>
      <preference id="41065">
        <name>topcoll_toggle_253</name>
        <value>::</value>
      </preference>
      <preference id="44293">
        <name>topcoll_toggle_254</name>
        <value>:j</value>
      </preference>
      <preference id="41708">
        <name>topcoll_toggle_255</name>
        <value>::</value>
      </preference>
      <preference id="43214">
        <name>topcoll_toggle_257</name>
        <value>yj</value>
      </preference>
      <preference id="43213">
        <name>topcoll_toggle_259</name>
        <value>y</value>
      </preference>
      <preference id="43180">
        <name>topcoll_toggle_261</name>
        <value>j:</value>
      </preference>
      <preference id="46100">
        <name>topcoll_toggle_262</name>
        <value></value>
      </preference>
      <preference id="46166">
        <name>topcoll_toggle_263</name>
        <value>yy</value>
      </preference>
      <preference id="46350">
        <name>topcoll_toggle_264</name>
        <value>R</value>
      </preference>
      <preference id="46361">
        <name>topcoll_toggle_265</name>
        <value>r</value>
      </preference>
      <preference id="46389">
        <name>topcoll_toggle_266</name>
        <value>r</value>
      </preference>
      <preference id="49945">
        <name>topcoll_toggle_268</name>
        <value>:</value>
      </preference>
      <preference id="52477">
        <name>topcoll_toggle_272</name>
        <value></value>
      </preference>
      <preference id="50226">
        <name>topcoll_toggle_273</name>
        <value>yZ</value>
      </preference>
      <preference id="36395">
        <name>topcoll_toggle_28</name>
        <value>y</value>
      </preference>
      <preference id="54063">
        <name>topcoll_toggle_286</name>
        <value>y</value>
      </preference>
      <preference id="54062">
        <name>topcoll_toggle_287</name>
        <value>v</value>
      </preference>
      <preference id="54216">
        <name>topcoll_toggle_289</name>
        <value>y</value>
      </preference>
      <preference id="57433">
        <name>topcoll_toggle_290</name>
        <value>j:</value>
      </preference>
      <preference id="58693">
        <name>topcoll_toggle_291</name>
        <value>::</value>
      </preference>
      <preference id="58694">
        <name>topcoll_toggle_292</name>
        <value>::</value>
      </preference>
      <preference id="57556">
        <name>topcoll_toggle_293</name>
        <value>::</value>
      </preference>
      <preference id="58695">
        <name>topcoll_toggle_294</name>
        <value>::</value>
      </preference>
      <preference id="58696">
        <name>topcoll_toggle_295</name>
        <value>::</value>
      </preference>
      <preference id="58697">
        <name>topcoll_toggle_296</name>
        <value>::</value>
      </preference>
      <preference id="59777">
        <name>topcoll_toggle_299</name>
        <value>v</value>
      </preference>
      <preference id="36397">
        <name>topcoll_toggle_65</name>
        <value></value>
      </preference>
      <preference id="36396">
        <name>topcoll_toggle_81</name>
        <value>y</value>
      </preference>
      <preference id="45558">
        <name>topcoll_toggle_82</name>
        <value>:</value>
      </preference>
      <preference id="53645">
        <name>userselector_autoselectunique</name>
        <value>0</value>
      </preference>
      <preference id="53644">
        <name>userselector_preserveselected</name>
        <value>0</value>
      </preference>
      <preference id="53646">
        <name>userselector_searchanywhere</name>
        <value>0</value>
      </preference>
    </preferences>
    <roles>
      <role_overrides>
      </role_overrides>
      <role_assignments>
      </role_assignments>
    </roles>
  </user>
  <user id="27815" contextid="56115">
    <username>ashley.garrigan@hecc.oregon.gov</username>
    <idnumber></idnumber>
    <email>ashley.garrigan@hecc.oregon.gov</email>
    <icq></icq>
    <skype></skype>
    <yahoo></yahoo>
    <aim></aim>
    <msn></msn>
    <phone1></phone1>
    <phone2></phone2>
    <institution></institution>
    <department></department>
    <address></address>
    <city></city>
    <country></country>
    <lastip>76.144.141.28</lastip>
    <picture>0</picture>
    <url></url>
    <description>$@NULL@$</description>
    <descriptionformat>1</descriptionformat>
    <imagealt>$@NULL@$</imagealt>
    <auth>saml2</auth>
    <firstnamephonetic>$@NULL@$</firstnamephonetic>
    <lastnamephonetic>$@NULL@$</lastnamephonetic>
    <middlename>$@NULL@$</middlename>
    <alternatename>$@NULL@$</alternatename>
    <firstname>Ashley</firstname>
    <lastname>Garrigan</lastname>
    <confirmed>1</confirmed>
    <policyagreed>0</policyagreed>
    <deleted>0</deleted>
    <lang>en</lang>
    <theme></theme>
    <timezone>99</timezone>
    <firstaccess>1641491482</firstaccess>
    <lastaccess>1707773696</lastaccess>
    <lastlogin>1706749557</lastlogin>
    <currentlogin>1707767390</currentlogin>
    <mailformat>1</mailformat>
    <maildigest>0</maildigest>
    <maildisplay>0</maildisplay>
    <autosubscribe>1</autosubscribe>
    <trackforums>0</trackforums>
    <timecreated>1641491482</timecreated>
    <timemodified>1707767390</timemodified>
    <trustbitmask>0</trustbitmask>
    <custom_fields>
      <custom_field id="1">
        <field_name>starusername</field_name>
        <field_type>text</field_type>
        <field_data>ashley.g</field_data>
      </custom_field>
    </custom_fields>
    <tags>
    </tags>
    <preferences>
      <preference id="44901">
        <name>core_message_migrate_data</name>
        <value>1</value>
      </preference>
      <preference id="55442">
        <name>topcoll_toggle_126</name>
        <value>B:</value>
      </preference>
      <preference id="44902">
        <name>topcoll_toggle_257</name>
        <value>::</value>
      </preference>
      <preference id="59601">
        <name>topcoll_toggle_268</name>
        <value>:</value>
      </preference>
      <preference id="59819">
        <name>topcoll_toggle_299</name>
        <value>Z</value>
      </preference>
    </preferences>
    <roles>
      <role_overrides>
      </role_overrides>
      <role_assignments>
      </role_assignments>
    </roles>
  </user>
  <user id="28069" contextid="56938">
    <username>sharon.grillett@tcatknoxville.edu</username>
    <idnumber></idnumber>
    <email>sharon.grillett@tcatknoxville.edu</email>
    <icq></icq>
    <skype></skype>
    <yahoo></yahoo>
    <aim></aim>
    <msn></msn>
    <phone1></phone1>
    <phone2></phone2>
    <institution></institution>
    <department></department>
    <address></address>
    <city></city>
    <country></country>
    <lastip>40.138.128.6</lastip>
    <picture>0</picture>
    <url></url>
    <description>$@NULL@$</description>
    <descriptionformat>1</descriptionformat>
    <imagealt>$@NULL@$</imagealt>
    <auth>saml2</auth>
    <firstnamephonetic>$@NULL@$</firstnamephonetic>
    <lastnamephonetic>$@NULL@$</lastnamephonetic>
    <middlename>$@NULL@$</middlename>
    <alternatename>$@NULL@$</alternatename>
    <firstname>Sharon</firstname>
    <lastname>Grillett</lastname>
    <confirmed>1</confirmed>
    <policyagreed>0</policyagreed>
    <deleted>0</deleted>
    <lang>en</lang>
    <theme></theme>
    <timezone>99</timezone>
    <firstaccess>1647005890</firstaccess>
    <lastaccess>1707766236</lastaccess>
    <lastlogin>1685726513</lastlogin>
    <currentlogin>1707753979</currentlogin>
    <mailformat>1</mailformat>
    <maildigest>0</maildigest>
    <maildisplay>0</maildisplay>
    <autosubscribe>1</autosubscribe>
    <trackforums>0</trackforums>
    <timecreated>1647005890</timecreated>
    <timemodified>1707753979</timemodified>
    <trustbitmask>0</trustbitmask>
    <custom_fields>
      <custom_field id="1">
        <field_name>starusername</field_name>
        <field_type>text</field_type>
        <field_data>S00247898@tbr.edu</field_data>
      </custom_field>
    </custom_fields>
    <tags>
    </tags>
    <preferences>
      <preference id="46024">
        <name>core_message_migrate_data</name>
        <value>1</value>
      </preference>
      <preference id="47404">
        <name>topcoll_toggle_126</name>
        <value>;:</value>
      </preference>
      <preference id="49746">
        <name>topcoll_toggle_131</name>
        <value>jJ</value>
      </preference>
      <preference id="47405">
        <name>topcoll_toggle_132</name>
        <value>:Z</value>
      </preference>
      <preference id="47463">
        <name>topcoll_toggle_133</name>
        <value>yy</value>
      </preference>
      <preference id="47401">
        <name>topcoll_toggle_137</name>
        <value>y</value>
      </preference>
      <preference id="47402">
        <name>topcoll_toggle_139</name>
        <value>:</value>
      </preference>
      <preference id="47400">
        <name>topcoll_toggle_168</name>
        <value>r</value>
      </preference>
      <preference id="47548">
        <name>topcoll_toggle_203</name>
        <value>:</value>
      </preference>
      <preference id="49747">
        <name>topcoll_toggle_257</name>
        <value>^:</value>
      </preference>
      <preference id="49748">
        <name>topcoll_toggle_259</name>
        <value>:</value>
      </preference>
      <preference id="46025">
        <name>topcoll_toggle_261</name>
        <value>b:</value>
      </preference>
      <preference id="47388">
        <name>topcoll_toggle_263</name>
        <value>::</value>
      </preference>
      <preference id="51356">
        <name>topcoll_toggle_268</name>
        <value>:</value>
      </preference>
      <preference id="59787">
        <name>topcoll_toggle_299</name>
        <value>Z</value>
      </preference>
    </preferences>
    <roles>
      <role_overrides>
      </role_overrides>
      <role_assignments>
      </role_assignments>
    </roles>
  </user>
  <user id="29765" contextid="62480">
    <username>catherine.o'neil@fldoe.org</username>
    <idnumber></idnumber>
    <email>Catherine.O'Neil@fldoe.org</email>
    <icq></icq>
    <skype></skype>
    <yahoo></yahoo>
    <aim></aim>
    <msn></msn>
    <phone1></phone1>
    <phone2></phone2>
    <institution></institution>
    <department></department>
    <address></address>
    <city></city>
    <country></country>
    <lastip>150.176.9.254</lastip>
    <picture>0</picture>
    <url></url>
    <description>$@NULL@$</description>
    <descriptionformat>1</descriptionformat>
    <imagealt>$@NULL@$</imagealt>
    <auth>saml2</auth>
    <firstnamephonetic>$@NULL@$</firstnamephonetic>
    <lastnamephonetic>$@NULL@$</lastnamephonetic>
    <middlename>$@NULL@$</middlename>
    <alternatename>$@NULL@$</alternatename>
    <firstname>Catherine</firstname>
    <lastname>O'Neil</lastname>
    <confirmed>1</confirmed>
    <policyagreed>0</policyagreed>
    <deleted>0</deleted>
    <lang>en</lang>
    <theme></theme>
    <timezone>99</timezone>
    <firstaccess>1680008132</firstaccess>
    <lastaccess>1707753896</lastaccess>
    <lastlogin>1701959432</lastlogin>
    <currentlogin>1707753896</currentlogin>
    <mailformat>1</mailformat>
    <maildigest>0</maildigest>
    <maildisplay>0</maildisplay>
    <autosubscribe>1</autosubscribe>
    <trackforums>0</trackforums>
    <timecreated>1680008132</timecreated>
    <timemodified>1707753896</timemodified>
    <trustbitmask>0</trustbitmask>
    <custom_fields>
      <custom_field id="1">
        <field_name>starusername</field_name>
        <field_type>text</field_type>
        <field_data>Catherine O'Neil</field_data>
      </custom_field>
    </custom_fields>
    <tags>
    </tags>
    <preferences>
      <preference id="53346">
        <name>core_message_migrate_data</name>
        <value>1</value>
      </preference>
      <preference id="53349">
        <name>topcoll_toggle_264</name>
        <value>y</value>
      </preference>
      <preference id="53542">
        <name>topcoll_toggle_265</name>
        <value>j</value>
      </preference>
      <preference id="59786">
        <name>topcoll_toggle_299</name>
        <value>:</value>
      </preference>
    </preferences>
    <roles>
      <role_overrides>
      </role_overrides>
      <role_assignments>
      </role_assignments>
    </roles>
  </user>
  <user id="29782" contextid="62513">
    <username>dfriend@air.org</username>
    <idnumber></idnumber>
    <email>dfriend@air.org</email>
    <icq></icq>
    <skype></skype>
    <yahoo></yahoo>
    <aim></aim>
    <msn></msn>
    <phone1></phone1>
    <phone2></phone2>
    <institution></institution>
    <department></department>
    <address></address>
    <city></city>
    <country></country>
    <lastip>2600:1700:b220:f1e0:4831:ba83:8142:9758</lastip>
    <picture>0</picture>
    <url></url>
    <description>$@NULL@$</description>
    <descriptionformat>1</descriptionformat>
    <imagealt>$@NULL@$</imagealt>
    <auth>saml2</auth>
    <firstnamephonetic>$@NULL@$</firstnamephonetic>
    <lastnamephonetic>$@NULL@$</lastnamephonetic>
    <middlename>$@NULL@$</middlename>
    <alternatename>$@NULL@$</alternatename>
    <firstname>Denise</firstname>
    <lastname>Friend</lastname>
    <confirmed>1</confirmed>
    <policyagreed>0</policyagreed>
    <deleted>0</deleted>
    <lang>en</lang>
    <theme></theme>
    <timezone>99</timezone>
    <firstaccess>1680177422</firstaccess>
    <lastaccess>1707752167</lastaccess>
    <lastlogin>1707584036</lastlogin>
    <currentlogin>1707752167</currentlogin>
    <mailformat>1</mailformat>
    <maildigest>0</maildigest>
    <maildisplay>0</maildisplay>
    <autosubscribe>1</autosubscribe>
    <trackforums>0</trackforums>
    <timecreated>1680177421</timecreated>
    <timemodified>1707752167</timemodified>
    <trustbitmask>0</trustbitmask>
    <custom_fields>
      <custom_field id="1">
        <field_name>starusername</field_name>
        <field_type>text</field_type>
        <field_data>dfriend</field_data>
      </custom_field>
    </custom_fields>
    <tags>
    </tags>
    <preferences>
      <preference id="53407">
        <name>core_message_migrate_data</name>
        <value>1</value>
      </preference>
      <preference id="58534">
        <name>topcoll_toggle_268</name>
        <value>:</value>
      </preference>
      <preference id="59780">
        <name>topcoll_toggle_299</name>
        <value>Z</value>
      </preference>
    </preferences>
    <roles>
      <role_overrides>
      </role_overrides>
      <role_assignments>
      </role_assignments>
    </roles>
  </user>
  <user id="31218" contextid="67766">
    <username>jritter@colleton.k12.sc.us</username>
    <idnumber></idnumber>
    <email>jritter@colleton.k12.sc.us</email>
    <icq></icq>
    <skype></skype>
    <yahoo></yahoo>
    <aim></aim>
    <msn></msn>
    <phone1></phone1>
    <phone2></phone2>
    <institution></institution>
    <department></department>
    <address></address>
    <city></city>
    <country></country>
    <lastip>165.166.3.78</lastip>
    <picture>0</picture>
    <url></url>
    <description>$@NULL@$</description>
    <descriptionformat>1</descriptionformat>
    <imagealt>$@NULL@$</imagealt>
    <auth>saml2</auth>
    <firstnamephonetic>$@NULL@$</firstnamephonetic>
    <lastnamephonetic>$@NULL@$</lastnamephonetic>
    <middlename>$@NULL@$</middlename>
    <alternatename>$@NULL@$</alternatename>
    <firstname>Joe</firstname>
    <lastname>Ritter</lastname>
    <confirmed>1</confirmed>
    <policyagreed>0</policyagreed>
    <deleted>0</deleted>
    <lang>en</lang>
    <theme></theme>
    <timezone>99</timezone>
    <firstaccess>1706194268</firstaccess>
    <lastaccess>1707760324</lastaccess>
    <lastlogin>1706194268</lastlogin>
    <currentlogin>1707759079</currentlogin>
    <mailformat>1</mailformat>
    <maildigest>0</maildigest>
    <maildisplay>0</maildisplay>
    <autosubscribe>1</autosubscribe>
    <trackforums>0</trackforums>
    <timecreated>1706194268</timecreated>
    <timemodified>1707759079</timemodified>
    <trustbitmask>0</trustbitmask>
    <custom_fields>
      <custom_field id="1">
        <field_name>starusername</field_name>
        <field_type>text</field_type>
        <field_data>jrit</field_data>
      </custom_field>
    </custom_fields>
    <tags>
    </tags>
    <preferences>
      <preference id="59445">
        <name>core_message_migrate_data</name>
        <value>1</value>
      </preference>
      <preference id="59805">
        <name>topcoll_toggle_299</name>
        <value>Z</value>
      </preference>
    </preferences>
    <roles>
      <role_overrides>
      </role_overrides>
      <role_assignments>
      </role_assignments>
    </roles>
  </user>
  <user id="31280" contextid="68006">
    <username>summer.morgan@ky.gov</username>
    <idnumber></idnumber>
    <email>summer.morgan@ky.gov</email>
    <icq></icq>
    <skype></skype>
    <yahoo></yahoo>
    <aim></aim>
    <msn></msn>
    <phone1></phone1>
    <phone2></phone2>
    <institution></institution>
    <department></department>
    <address></address>
    <city></city>
    <country></country>
    <lastip>174.163.133.76</lastip>
    <picture>0</picture>
    <url></url>
    <description>$@NULL@$</description>
    <descriptionformat>1</descriptionformat>
    <imagealt>$@NULL@$</imagealt>
    <auth>saml2</auth>
    <firstnamephonetic>$@NULL@$</firstnamephonetic>
    <lastnamephonetic>$@NULL@$</lastnamephonetic>
    <middlename>$@NULL@$</middlename>
    <alternatename>$@NULL@$</alternatename>
    <firstname>Summer</firstname>
    <lastname>Morgan</lastname>
    <confirmed>1</confirmed>
    <policyagreed>0</policyagreed>
    <deleted>0</deleted>
    <lang>en</lang>
    <theme></theme>
    <timezone>99</timezone>
    <firstaccess>1707755886</firstaccess>
    <lastaccess>1707755961</lastaccess>
    <lastlogin>0</lastlogin>
    <currentlogin>1707755886</currentlogin>
    <mailformat>1</mailformat>
    <maildigest>0</maildigest>
    <maildisplay>0</maildisplay>
    <autosubscribe>1</autosubscribe>
    <trackforums>0</trackforums>
    <timecreated>1707755886</timecreated>
    <timemodified>1707755886</timemodified>
    <trustbitmask>0</trustbitmask>
    <custom_fields>
      <custom_field id="1">
        <field_name>starusername</field_name>
        <field_type>text</field_type>
        <field_data>smorgan</field_data>
      </custom_field>
    </custom_fields>
    <tags>
    </tags>
    <preferences>
      <preference id="59789">
        <name>core_message_migrate_data</name>
        <value>1</value>
      </preference>
      <preference id="59793">
        <name>topcoll_toggle_261</name>
        <value>::</value>
      </preference>
      <preference id="59790">
        <name>topcoll_toggle_264</name>
        <value>:</value>
      </preference>
      <preference id="59795">
        <name>topcoll_toggle_268</name>
        <value>:</value>
      </preference>
      <preference id="59791">
        <name>topcoll_toggle_299</name>
        <value>:</value>
      </preference>
    </preferences>
    <roles>
      <role_overrides>
      </role_overrides>
      <role_assignments>
      </role_assignments>
    </roles>
  </user>
  <user id="31282" contextid="68008">
    <username>heather.ballard@ky.gov</username>
    <idnumber></idnumber>
    <email>heather.ballard@ky.gov</email>
    <icq></icq>
    <skype></skype>
    <yahoo></yahoo>
    <aim></aim>
    <msn></msn>
    <phone1></phone1>
    <phone2></phone2>
    <institution></institution>
    <department></department>
    <address></address>
    <city></city>
    <country></country>
    <lastip>205.204.186.55</lastip>
    <picture>0</picture>
    <url></url>
    <description>$@NULL@$</description>
    <descriptionformat>1</descriptionformat>
    <imagealt>$@NULL@$</imagealt>
    <auth>saml2</auth>
    <firstnamephonetic>$@NULL@$</firstnamephonetic>
    <lastnamephonetic>$@NULL@$</lastnamephonetic>
    <middlename>$@NULL@$</middlename>
    <alternatename>$@NULL@$</alternatename>
    <firstname>Heather</firstname>
    <lastname>Ballard</lastname>
    <confirmed>1</confirmed>
    <policyagreed>0</policyagreed>
    <deleted>0</deleted>
    <lang>en</lang>
    <theme></theme>
    <timezone>99</timezone>
    <firstaccess>1707757392</firstaccess>
    <lastaccess>1707759326</lastaccess>
    <lastlogin>0</lastlogin>
    <currentlogin>1707757392</currentlogin>
    <mailformat>1</mailformat>
    <maildigest>0</maildigest>
    <maildisplay>0</maildisplay>
    <autosubscribe>1</autosubscribe>
    <trackforums>0</trackforums>
    <timecreated>1707757392</timecreated>
    <timemodified>1707757392</timemodified>
    <trustbitmask>0</trustbitmask>
    <custom_fields>
      <custom_field id="1">
        <field_name>starusername</field_name>
        <field_type>text</field_type>
        <field_data>HeatherBallard</field_data>
      </custom_field>
    </custom_fields>
    <tags>
    </tags>
    <preferences>
      <preference id="59796">
        <name>core_message_migrate_data</name>
        <value>1</value>
      </preference>
      <preference id="59799">
        <name>topcoll_toggle_261</name>
        <value>::</value>
      </preference>
      <preference id="59797">
        <name>topcoll_toggle_264</name>
        <value>y</value>
      </preference>
      <preference id="59800">
        <name>topcoll_toggle_268</name>
        <value>:</value>
      </preference>
      <preference id="59798">
        <name>topcoll_toggle_299</name>
        <value>:</value>
      </preference>
    </preferences>
    <roles>
      <role_overrides>
      </role_overrides>
      <role_assignments>
      </role_assignments>
    </roles>
  </user>
  <user id="31283" contextid="68009">
    <username>dfaubus@vbsd.us</username>
    <idnumber></idnumber>
    <email>dfaubus@vbsd.us</email>
    <icq></icq>
    <skype></skype>
    <yahoo></yahoo>
    <aim></aim>
    <msn></msn>
    <phone1></phone1>
    <phone2></phone2>
    <institution></institution>
    <department></department>
    <address></address>
    <city></city>
    <country></country>
    <lastip>98.187.161.45</lastip>
    <picture>0</picture>
    <url></url>
    <description>$@NULL@$</description>
    <descriptionformat>1</descriptionformat>
    <imagealt>$@NULL@$</imagealt>
    <auth>saml2</auth>
    <firstnamephonetic>$@NULL@$</firstnamephonetic>
    <lastnamephonetic>$@NULL@$</lastnamephonetic>
    <middlename>$@NULL@$</middlename>
    <alternatename>$@NULL@$</alternatename>
    <firstname>Deborah</firstname>
    <lastname>Faubus</lastname>
    <confirmed>1</confirmed>
    <policyagreed>0</policyagreed>
    <deleted>0</deleted>
    <lang>en</lang>
    <theme></theme>
    <timezone>99</timezone>
    <firstaccess>1707758306</firstaccess>
    <lastaccess>1707759518</lastaccess>
    <lastlogin>0</lastlogin>
    <currentlogin>1707758306</currentlogin>
    <mailformat>1</mailformat>
    <maildigest>0</maildigest>
    <maildisplay>0</maildisplay>
    <autosubscribe>1</autosubscribe>
    <trackforums>0</trackforums>
    <timecreated>1707758306</timecreated>
    <timemodified>1707758306</timemodified>
    <trustbitmask>0</trustbitmask>
    <custom_fields>
      <custom_field id="1">
        <field_name>starusername</field_name>
        <field_type>text</field_type>
        <field_data>Deborah Faubus</field_data>
      </custom_field>
    </custom_fields>
    <tags>
    </tags>
    <preferences>
      <preference id="59803">
        <name>core_message_migrate_data</name>
        <value>1</value>
      </preference>
      <preference id="59804">
        <name>topcoll_toggle_273</name>
        <value>b:</value>
      </preference>
      <preference id="59806">
        <name>topcoll_toggle_299</name>
        <value>J</value>
      </preference>
    </preferences>
    <roles>
      <role_overrides>
      </role_overrides>
      <role_assignments>
      </role_assignments>
    </roles>
  </user>
  <user id="31284" contextid="68018">
    <username>mahalia.baldini@twc.texas.gov</username>
    <idnumber></idnumber>
    <email>mahalia.baldini@twc.texas.gov</email>
    <icq></icq>
    <skype></skype>
    <yahoo></yahoo>
    <aim></aim>
    <msn></msn>
    <phone1></phone1>
    <phone2></phone2>
    <institution></institution>
    <department></department>
    <address></address>
    <city></city>
    <country></country>
    <lastip>74.192.32.148</lastip>
    <picture>0</picture>
    <url></url>
    <description>$@NULL@$</description>
    <descriptionformat>1</descriptionformat>
    <imagealt>$@NULL@$</imagealt>
    <auth>saml2</auth>
    <firstnamephonetic>$@NULL@$</firstnamephonetic>
    <lastnamephonetic>$@NULL@$</lastnamephonetic>
    <middlename>$@NULL@$</middlename>
    <alternatename>$@NULL@$</alternatename>
    <firstname>Mahalia</firstname>
    <lastname>Baldini</lastname>
    <confirmed>1</confirmed>
    <policyagreed>0</policyagreed>
    <deleted>0</deleted>
    <lang>en</lang>
    <theme></theme>
    <timezone>99</timezone>
    <firstaccess>1707762219</firstaccess>
    <lastaccess>1707762219</lastaccess>
    <lastlogin>0</lastlogin>
    <currentlogin>1707762219</currentlogin>
    <mailformat>1</mailformat>
    <maildigest>0</maildigest>
    <maildisplay>0</maildisplay>
    <autosubscribe>1</autosubscribe>
    <trackforums>0</trackforums>
    <timecreated>1707762219</timecreated>
    <timemodified>1707762219</timemodified>
    <trustbitmask>0</trustbitmask>
    <custom_fields>
      <custom_field id="1">
        <field_name>starusername</field_name>
        <field_type>text</field_type>
        <field_data>mahalia.baldini@twc.texas.gov</field_data>
      </custom_field>
    </custom_fields>
    <tags>
    </tags>
    <preferences>
      <preference id="59808">
        <name>core_message_migrate_data</name>
        <value>1</value>
      </preference>
      <preference id="59809">
        <name>topcoll_toggle_299</name>
        <value>y</value>
      </preference>
    </preferences>
    <roles>
      <role_overrides>
      </role_overrides>
      <role_assignments>
      </role_assignments>
    </roles>
  </user>
  <user id="31287" contextid="68029">
    <username>greg.long@ky.gov</username>
    <idnumber></idnumber>
    <email>greg.long@ky.gov</email>
    <icq></icq>
    <skype></skype>
    <yahoo></yahoo>
    <aim></aim>
    <msn></msn>
    <phone1></phone1>
    <phone2></phone2>
    <institution></institution>
    <department></department>
    <address></address>
    <city></city>
    <country></country>
    <lastip>217.180.201.86</lastip>
    <picture>0</picture>
    <url></url>
    <description>I love God</description>
    <descriptionformat>1</descriptionformat>
    <imagealt>$@NULL@$</imagealt>
    <auth>saml2</auth>
    <firstnamephonetic>$@NULL@$</firstnamephonetic>
    <lastnamephonetic>$@NULL@$</lastnamephonetic>
    <middlename>$@NULL@$</middlename>
    <alternatename>$@NULL@$</alternatename>
    <firstname>Greg</firstname>
    <lastname>Long</lastname>
    <confirmed>1</confirmed>
    <policyagreed>0</policyagreed>
    <deleted>0</deleted>
    <lang>en</lang>
    <theme></theme>
    <timezone>99</timezone>
    <firstaccess>1707780759</firstaccess>
    <lastaccess>1707781079</lastaccess>
    <lastlogin>1707780759</lastlogin>
    <currentlogin>1707781079</currentlogin>
    <mailformat>1</mailformat>
    <maildigest>0</maildigest>
    <maildisplay>0</maildisplay>
    <autosubscribe>1</autosubscribe>
    <trackforums>0</trackforums>
    <timecreated>1707780759</timecreated>
    <timemodified>1707781079</timemodified>
    <trustbitmask>0</trustbitmask>
    <custom_fields>
      <custom_field id="1">
        <field_name>starusername</field_name>
        <field_type>text</field_type>
        <field_data>greg.long</field_data>
      </custom_field>
    </custom_fields>
    <tags>
    </tags>
    <preferences>
      <preference id="59822">
        <name>core_message_migrate_data</name>
        <value>1</value>
      </preference>
      <preference id="59829">
        <name>topcoll_toggle_168</name>
        <value>:</value>
      </preference>
      <preference id="59830">
        <name>topcoll_toggle_203</name>
        <value>:</value>
      </preference>
      <preference id="59827">
        <name>topcoll_toggle_261</name>
        <value>::</value>
      </preference>
      <preference id="59825">
        <name>topcoll_toggle_264</name>
        <value>:</value>
      </preference>
      <preference id="59824">
        <name>topcoll_toggle_265</name>
        <value>:</value>
      </preference>
      <preference id="59823">
        <name>topcoll_toggle_266</name>
        <value>:</value>
      </preference>
      <preference id="59828">
        <name>topcoll_toggle_268</name>
        <value>:</value>
      </preference>
      <preference id="59826">
        <name>topcoll_toggle_299</name>
        <value>:</value>
      </preference>
    </preferences>
    <roles>
      <role_overrides>
      </role_overrides>
      <role_assignments>
      </role_assignments>
    </roles>
  </user>
</users>